csromer/__init__.py
csromer-0.0.2.dist-info/LICENSE
csromer-0.0.2.dist-info/METADATA
csromer-0.0.2.dist-info/WHEEL
csromer-0.0.2.dist-info/top_level.txt
csromer-0.0.2.dist-info/RECORD
