Metadata-Version: 2.1
Name: csromer
Version: 0.0.2
Summary: Compressed Sensing Rotation Measure Reconstructor
Home-page: https://github.com/miguelcarcamov/csromer
Author: Miguel Carcamo
Author-email: miguel.carcamo@manchester.ac.uk
License: GNU GPL
Platform: UNKNOWN
License-File: LICENSE
Requires-Dist: proxmin (>=0.6.11)
Requires-Dist: PyWavelets (>=1.1.1)
Requires-Dist: matplotlib (>=3.4.2)
Requires-Dist: prox-tv (>=3.2.1)
Requires-Dist: numpy (>=1.20.3)
Requires-Dist: pynufft (>=2021.2.0)
Requires-Dist: scipy (>=1.6.3)
Requires-Dist: astropy (>=4.2.1)
Requires-Dist: joblib (>=1.0.1)
Requires-Dist: astroquery (>=0.4.4)
Requires-Dist: h5py (>=3.1.0)
Requires-Dist: astropy-healpix (>=0.6)
